[{"county":"Alt Urgell","c_preci_mm":504.1,"c_wspeed_ms":60,"X7":"SW","year":2015,"c_temp_ave":12.2,"c_temp_avemax":20.2,"c_temp_avemin":5.7,"w_domestic_consump":45.19,"w_industry_consump":21.33,"w_total_network":66.52,"w_own_sources":38.78,"w_total":105.3,"p_population.x":20695,"area_km2.x":1448,"p_density_hkm2.x":14.29,"f_cleared_ha":0.01,"f_reforested_ha":0,"f_relative_reforested":0,"l_forests":56.12,"l_bushes":24.18,"l_others":12.08,"l_novege":1.84,"l_crop_dry":3.01,"l_crop_irri":1.24,"l_urban":1.46,"p_population.y":20695,"area_km2.y":1448,"p_density_hkm2.y":14.29},{"county":"Alta Ribagorça","c_preci_mm":680.3,"c_wspeed_ms":71,"X7":"N","year":2015,"c_temp_ave":10.8,"c_temp_avemax":20.1,"c_temp_avemin":3.7,"w_domestic_consump":102.06,"w_industry_consump":6.77,"w_total_network":108.83,"w_own_sources":36.56,"w_total":145.37,"p_population.x":3884,"area_km2.x":427,"p_density_hkm2.x":9.1,"f_cleared_ha":0,"f_reforested_ha":0,"f_relative_reforested":0,"l_forests":36.48,"l_bushes":18,"l_others":40.57,"l_novege":2.38,"l_crop_dry":1.36,"l_crop_irri":0.45,"l_urban":0.96,"p_population.y":3884,"area_km2.y":427,"p_density_hkm2.y":9.1},{"county":"Aran","c_preci_mm":960.9,"c_wspeed_ms":70,"X7":"S","year":2015,"c_temp_ave":9.9,"c_temp_avemax":16.9,"c_temp_avemin":5.3,"w_domestic_consump":115.62,"w_industry_consump":23.57,"w_total_network":139.19,"w_own_sources":41.37,"w_total":180.56,"p_population.x":9926,"area_km2.x":634,"p_density_hkm2.x":15.66,"f_cleared_ha":0,"f_reforested_ha":0,"l_forests":37.31,"l_bushes":28.21,"l_others":31.69,"l_novege":1.48,"l_crop_dry":0.07,"l_crop_irri":0,"l_urban":1.07,"p_population.y":9926,"area_km2.y":634,"p_density_hkm2.y":15.66},{"county":"Berguedà","c_preci_mm":581.1,"c_wspeed_ms":71,"X7":"SW","year":2015,"c_temp_ave":12.5,"c_temp_avemax":19.8,"c_temp_avemin":7.6,"w_domestic_consump":36.02,"w_industry_consump":18.67,"w_total_network":54.7,"w_own_sources":1.1,"w_total":55.8,"p_population.x":39517,"area_km2.x":1185,"p_density_hkm2.x":33.35,"f_cleared_ha":0.11,"f_reforested_ha":0.01,"f_relative_reforested":4.64,"l_forests":60.41,"l_bushes":15.95,"l_others":11.13,"l_novege":1.86,"l_crop_dry":8.57,"l_crop_irri":0.04,"l_urban":2.05,"p_population.y":39517,"area_km2.y":1185,"p_density_hkm2.y":33.35},{"county":"Cerdanya","c_preci_mm":601,"c_wspeed_ms":67,"X7":"E","year":2015,"c_temp_ave":8.9,"c_temp_avemax":18.3,"c_temp_avemin":0.9,"w_domestic_consump":71.89,"w_industry_consump":25.18,"w_total_network":97.07,"w_own_sources":60.03,"w_total":157.1,"p_population.x":17870,"area_km2.x":547,"p_density_hkm2.x":32.67,"f_cleared_ha":0,"f_reforested_ha":0,"l_forests":45.78,"l_bushes":14.71,"l_others":28.91,"l_novege":1.96,"l_crop_dry":3.89,"l_crop_irri":1.5,"l_urban":3.8,"p_population.y":17870,"area_km2.y":547,"p_density_hkm2.y":32.67},{"county":"Pallars Jussà","c_preci_mm":509.2,"c_wspeed_ms":64,"X7":"N","year":2015,"c_temp_ave":13.4,"c_temp_avemax":21,"c_temp_avemin":6.8,"w_domestic_consump":54.13,"w_industry_consump":9.35,"w_total_network":63.47,"w_own_sources":4.99,"w_total":68.46,"p_population.x":13609,"area_km2.x":1343,"p_density_hkm2.x":10.13,"f_cleared_ha":0.11,"f_reforested_ha":0,"f_relative_reforested":1.04,"l_forests":33.62,"l_bushes":36.3,"l_others":11.86,"l_novege":3,"l_crop_dry":11.56,"l_crop_irri":2.07,"l_urban":1.66,"p_population.y":13609,"area_km2.y":1343,"p_density_hkm2.y":10.13},{"county":"Pallars Sobirà","c_preci_mm":616.6,"c_wspeed_ms":68,"X7":"..","year":2015,"c_temp_ave":11.9,"c_temp_avemax":20.1,"c_temp_avemin":5.4,"w_domestic_consump":76.01,"w_industry_consump":18.24,"w_total_network":94.24,"w_own_sources":67.78,"w_total":162.01,"p_population.x":7060,"area_km2.x":1378,"p_density_hkm2.x":5.12,"f_cleared_ha":0,"f_reforested_ha":0,"f_relative_reforested":0,"l_forests":42.88,"l_bushes":32.03,"l_others":20.52,"l_novege":1.31,"l_crop_dry":0.75,"l_crop_irri":0.13,"l_urban":0.99,"p_population.y":7060,"area_km2.y":1378,"p_density_hkm2.y":5.12},{"county":"Ripollès","c_preci_mm":958.9,"c_wspeed_ms":78,"X7":"SW","year":2015,"c_temp_ave":10.6,"c_temp_avemax":18.2,"c_temp_avemin":4.4,"w_domestic_consump":41.55,"w_industry_consump":14.56,"w_total_network":56.1,"w_own_sources":29.94,"w_total":86.04,"p_population.x":25342,"area_km2.x":957,"p_density_hkm2.x":26.48,"f_cleared_ha":0.01,"f_reforested_ha":0,"f_relative_reforested":0,"l_forests":61.74,"l_bushes":11.88,"l_others":22.02,"l_novege":0.88,"l_crop_dry":1.85,"l_crop_irri":0,"l_urban":1.73,"p_population.y":25342,"area_km2.y":957,"p_density_hkm2.y":26.48},{"county":"Solsonès","c_preci_mm":447.3,"c_wspeed_ms":74,"X7":"W","year":2015,"c_temp_ave":12.5,"c_temp_avemax":19,"c_temp_avemin":7.1,"w_domestic_consump":42.04,"w_industry_consump":26.32,"w_total_network":68.36,"w_own_sources":17.66,"w_total":86.01,"p_population.x":13414,"area_km2.x":1001,"p_density_hkm2.x":13.4,"f_cleared_ha":0.23,"f_reforested_ha":0,"f_relative_reforested":0,"l_forests":58.52,"l_bushes":14.6,"l_others":5.92,"l_novege":1.67,"l_crop_dry":17.71,"l_crop_irri":0.05,"l_urban":1.61,"p_population.y":13414,"area_km2.y":1001,"p_density_hkm2.y":13.4},{"county":"Alt Urgell","c_preci_mm":601.7,"c_wspeed_ms":63,"X7":"SW","year":2016,"c_temp_ave":11.7,"c_temp_avemax":19.3,"c_temp_avemin":5.4,"w_domestic_consump":46.1,"w_industry_consump":22.16,"w_total_network":68.26,"w_own_sources":36.84,"w_total":105.1,"p_population.x":20548,"area_km2.x":1448,"p_density_hkm2.x":14.19,"f_cleared_ha":0.02,"f_reforested_ha":0,"f_relative_reforested":0,"l_forests":56.12,"l_bushes":24.18,"l_others":11.9,"l_novege":1.96,"l_crop_dry":3.03,"l_crop_irri":1.28,"l_urban":1.46,"p_population.y":20548,"area_km2.y":1448,"p_density_hkm2.y":14.19},{"county":"Alta Ribagorça","c_preci_mm":753,"c_wspeed_ms":73,"X7":"N","year":2016,"c_temp_ave":10.4,"c_temp_avemax":19.5,"c_temp_avemin":3.3,"w_domestic_consump":102.2,"w_industry_consump":1.22,"w_total_network":103.41,"w_own_sources":44.53,"w_total":147.94,"p_population.x":3867,"area_km2.x":427,"p_density_hkm2.x":9.06,"f_cleared_ha":0.02,"f_reforested_ha":0,"f_relative_reforested":0,"l_forests":36.48,"l_bushes":18,"l_others":40.59,"l_novege":2.39,"l_crop_dry":1.36,"l_crop_irri":0.45,"l_urban":0.94,"p_population.y":3867,"area_km2.y":427,"p_density_hkm2.y":9.06},{"county":"Aran","c_preci_mm":686.2,"c_wspeed_ms":70,"X7":"S","year":2016,"c_temp_ave":9.8,"c_temp_avemax":16.5,"c_temp_avemin":5.2,"w_domestic_consump":121.26,"w_industry_consump":30.41,"w_total_network":151.68,"w_own_sources":71.07,"w_total":222.75,"p_population.x":9930,"area_km2.x":634,"p_density_hkm2.x":15.66,"f_cleared_ha":0,"f_reforested_ha":0,"l_forests":37.31,"l_bushes":28.21,"l_others":31.68,"l_novege":1.47,"l_crop_dry":0.07,"l_crop_irri":0,"l_urban":1.08,"p_population.y":9930,"area_km2.y":634,"p_density_hkm2.y":15.66},{"county":"Berguedà","c_preci_mm":619.9,"c_wspeed_ms":73,"X7":"SW","year":2016,"c_temp_ave":12.1,"c_temp_avemax":19.4,"c_temp_avemin":7.2,"w_domestic_consump":34.42,"w_industry_consump":17.79,"w_total_network":52.21,"w_own_sources":1.38,"w_total":53.59,"p_population.x":39178,"area_km2.x":1185,"p_density_hkm2.x":33.06,"f_cleared_ha":0.12,"f_reforested_ha":0,"f_relative_reforested":0,"l_forests":60.41,"l_bushes":15.91,"l_others":11.19,"l_novege":1.72,"l_crop_dry":8.66,"l_crop_irri":0.05,"l_urban":2.08,"p_population.y":39178,"area_km2.y":1185,"p_density_hkm2.y":33.06},{"county":"Cerdanya","c_preci_mm":553.5,"c_wspeed_ms":69,"X7":"E","year":2016,"c_temp_ave":8.7,"c_temp_avemax":17.8,"c_temp_avemin":0.8,"w_domestic_consump":75.63,"w_industry_consump":31.29,"w_total_network":106.91,"w_own_sources":75.94,"w_total":182.86,"p_population.x":17704,"area_km2.x":547,"p_density_hkm2.x":32.37,"f_cleared_ha":0,"f_reforested_ha":0,"f_relative_reforested":0,"l_forests":45.78,"l_bushes":14.72,"l_others":29.06,"l_novege":1.93,"l_crop_dry":3.8,"l_crop_irri":1.45,"l_urban":3.82,"p_population.y":17704,"area_km2.y":547,"p_density_hkm2.y":32.37},{"county":"Pallars Jussà","X7":"..","year":2016,"w_domestic_consump":53.67,"w_industry_consump":10.18,"w_total_network":63.85,"w_own_sources":4.93,"w_total":68.78,"p_population.x":13453,"area_km2.x":1343,"p_density_hkm2.x":10.02,"f_cleared_ha":0.03,"f_reforested_ha":0,"f_relative_reforested":0,"l_forests":33.62,"l_bushes":36.23,"l_others":11.86,"l_novege":3.01,"l_crop_dry":11.63,"l_crop_irri":2.08,"l_urban":1.66,"p_population.y":13453,"area_km2.y":1343,"p_density_hkm2.y":10.02},{"county":"Pallars Sobirà","c_preci_mm":674.2,"c_wspeed_ms":69,"X7":"..","year":2016,"c_temp_ave":11.6,"c_temp_avemax":19.5,"c_temp_avemin":5.1,"w_domestic_consump":78.11,"w_industry_consump":19.25,"w_total_network":97.37,"w_own_sources":63.6,"w_total":160.96,"p_population.x":6986,"area_km2.x":1378,"p_density_hkm2.x":5.07,"f_cleared_ha":0,"f_reforested_ha":0,"f_relative_reforested":0,"l_forests":42.88,"l_bushes":32.03,"l_others":20.51,"l_novege":1.31,"l_crop_dry":0.75,"l_crop_irri":0.13,"l_urban":0.99,"p_population.y":6986,"area_km2.y":1378,"p_density_hkm2.y":5.07},{"county":"Ripollès","c_preci_mm":936.2,"c_wspeed_ms":80,"X7":"SW","year":2016,"c_temp_ave":10.4,"c_temp_avemax":17.6,"c_temp_avemin":4.4,"w_domestic_consump":43.34,"w_industry_consump":15.43,"w_total_network":58.77,"w_own_sources":29.41,"w_total":88.18,"p_population.x":25101,"area_km2.x":957,"p_density_hkm2.x":26.23,"f_cleared_ha":0,"f_reforested_ha":0,"f_relative_reforested":0,"l_forests":61.73,"l_bushes":11.91,"l_others":22.04,"l_novege":0.88,"l_crop_dry":1.82,"l_crop_irri":0,"l_urban":1.72,"p_population.y":25101,"area_km2.y":957,"p_density_hkm2.y":26.23},{"county":"Solsonès","c_preci_mm":429.7,"c_wspeed_ms":75,"X7":"W","year":2016,"c_temp_ave":12.4,"c_temp_avemax":19,"c_temp_avemin":6.9,"w_domestic_consump":42.4,"w_industry_consump":29.59,"w_total_network":71.99,"w_own_sources":22.31,"w_total":94.3,"p_population.x":13313,"area_km2.x":1001,"p_density_hkm2.x":13.3,"f_cleared_ha":0.21,"f_reforested_ha":0,"f_relative_reforested":0,"l_forests":58.52,"l_bushes":14.49,"l_others":5.58,"l_novege":1.66,"l_crop_dry":18.16,"l_crop_irri":0.05,"l_urban":1.62,"p_population.y":13313,"area_km2.y":1001,"p_density_hkm2.y":13.3},{"county":"Alt Urgell","c_preci_mm":482.7,"c_wspeed_ms":60,"X7":"SW","year":2017,"c_temp_ave":12.2,"c_temp_avemax":20.2,"c_temp_avemin":5.4,"w_domestic_consump":46.32,"w_industry_consump":28.58,"w_total_network":74.91,"w_own_sources":39.3,"w_total":114.2,"p_population.x":20296,"area_km2.x":1447,"p_density_hkm2.x":14.03,"f_cleared_ha":0.03,"f_reforested_ha":0,"f_relative_reforested":0,"l_forests":56.16,"l_bushes":24.19,"l_others":12,"l_novege":1.99,"l_crop_dry":2.97,"l_crop_irri":1.22,"l_urban":1.46,"p_population.y":20296,"area_km2.y":1447,"p_density_hkm2.y":14.03},{"county":"Alta Ribagorça","c_preci_mm":638.6,"c_wspeed_ms":70,"X7":"SE","year":2017,"c_temp_ave":10.5,"c_temp_avemax":20.2,"c_temp_avemin":3,"w_domestic_consump":114.92,"w_industry_consump":21.22,"w_total_network":136.14,"w_own_sources":31.25,"w_total":167.42,"p_population.x":3827,"area_km2.x":427,"p_density_hkm2.x":8.96,"f_cleared_ha":0,"f_reforested_ha":0,"l_forests":36.48,"l_bushes":18.16,"l_others":40.11,"l_novege":2.7,"l_crop_dry":1.37,"l_crop_irri":0.46,"l_urban":0.93,"p_population.y":3827,"area_km2.y":427,"p_density_hkm2.y":8.96},{"county":"Aran","c_preci_mm":859.1,"c_wspeed_ms":72,"X7":"S","year":2017,"c_temp_ave":9.7,"c_temp_avemax":16.8,"c_temp_avemin":4.8,"w_domestic_consump":124.21,"w_industry_consump":9.63,"w_total_network":133.85,"w_own_sources":84.79,"w_total":218.63,"p_population.x":9985,"area_km2.x":634,"p_density_hkm2.x":15.75,"f_cleared_ha":0,"f_reforested_ha":0,"l_forests":37.3,"l_bushes":28.21,"l_others":31.7,"l_novege":1.46,"l_crop_dry":0.07,"l_crop_irri":0,"l_urban":1.09,"p_population.y":9985,"area_km2.y":634,"p_density_hkm2.y":15.75},{"county":"Berguedà","c_preci_mm":493.6,"c_wspeed_ms":70,"X7":"SW","year":2017,"c_temp_ave":12.5,"c_temp_avemax":19.9,"c_temp_avemin":7.3,"w_domestic_consump":34.98,"w_industry_consump":18.95,"w_total_network":53.92,"w_own_sources":1.46,"w_total":55.38,"p_population.x":39013,"area_km2.x":1185,"p_density_hkm2.x":32.92,"f_cleared_ha":0.17,"f_reforested_ha":0,"f_relative_reforested":0,"l_forests":60.38,"l_bushes":15.87,"l_others":11.16,"l_novege":1.69,"l_crop_dry":8.78,"l_crop_irri":0.04,"l_urban":2.09,"p_population.y":39013,"area_km2.y":1185,"p_density_hkm2.y":32.92},{"county":"Cerdanya","c_preci_mm":618.8,"c_wspeed_ms":61,"X7":"NE","year":2017,"c_temp_ave":9.8,"c_temp_avemax":17.4,"c_temp_avemin":3.5,"w_domestic_consump":78.19,"w_industry_consump":28.16,"w_total_network":106.36,"w_own_sources":80.77,"w_total":187.13,"p_population.x":17623,"area_km2.x":547,"p_density_hkm2.x":32.22,"f_cleared_ha":0,"f_reforested_ha":0,"l_forests":45.78,"l_bushes":14.71,"l_others":29.14,"l_novege":1.94,"l_crop_dry":3.72,"l_crop_irri":1.42,"l_urban":3.83,"p_population.y":17623,"area_km2.y":547,"p_density_hkm2.y":32.22},{"county":"Pallars Jussà","c_preci_mm":456.4,"c_wspeed_ms":64,"X7":"N","year":2017,"c_temp_ave":13.3,"c_temp_avemax":21.4,"c_temp_avemin":6.6,"w_domestic_consump":55.53,"w_industry_consump":10.72,"w_total_network":66.25,"w_own_sources":7.14,"w_total":73.38,"p_population.x":13280,"area_km2.x":1343,"p_density_hkm2.x":9.89,"f_cleared_ha":0.06,"f_reforested_ha":0,"f_relative_reforested":0,"l_forests":33.62,"l_bushes":36.23,"l_others":12.11,"l_novege":3,"l_crop_dry":11.43,"l_crop_irri":2.04,"l_urban":1.66,"p_population.y":13280,"area_km2.y":1343,"p_density_hkm2.y":9.89},{"county":"Pallars Sobirà","c_preci_mm":624.9,"c_wspeed_ms":65,"X7":"..","year":2017,"c_temp_ave":12,"c_temp_avemax":20.4,"c_temp_avemin":4.9,"w_domestic_consump":77.76,"w_industry_consump":17.52,"w_total_network":95.28,"w_own_sources":57.46,"w_total":152.74,"p_population.x":6947,"area_km2.x":1378,"p_density_hkm2.x":5.04,"f_cleared_ha":0.01,"f_reforested_ha":0,"f_relative_reforested":0,"l_forests":42.88,"l_bushes":32.02,"l_others":20.52,"l_novege":1.31,"l_crop_dry":0.75,"l_crop_irri":0.13,"l_urban":1,"p_population.y":6947,"area_km2.y":1378,"p_density_hkm2.y":5.04},{"county":"Ripollès","c_preci_mm":852,"c_wspeed_ms":77,"X7":"SW","year":2017,"c_temp_ave":10.5,"c_temp_avemax":18.2,"c_temp_avemin":4.1,"w_domestic_consump":43.19,"w_industry_consump":16.83,"w_total_network":60.01,"w_own_sources":29.48,"w_total":89.5,"p_population.x":24999,"area_km2.x":957,"p_density_hkm2.x":26.12,"f_cleared_ha":0,"f_reforested_ha":0,"f_relative_reforested":0,"l_forests":61.73,"l_bushes":11.9,"l_others":22.05,"l_novege":0.89,"l_crop_dry":1.82,"l_crop_irri":0,"l_urban":1.71,"p_population.y":24999,"area_km2.y":957,"p_density_hkm2.y":26.12},{"county":"Solsonès","c_preci_mm":419.9,"c_wspeed_ms":73,"X7":"W","year":2017,"c_temp_ave":12.6,"c_temp_avemax":19.2,"c_temp_avemin":7,"w_domestic_consump":43.47,"w_industry_consump":24.79,"w_total_network":68.26,"w_own_sources":22.07,"w_total":90.33,"p_population.x":13360,"area_km2.x":1001,"p_density_hkm2.x":13.35,"f_cleared_ha":0.17,"f_reforested_ha":0,"f_relative_reforested":0,"l_forests":58.52,"l_bushes":14.6,"l_others":5.63,"l_novege":1.69,"l_crop_dry":18,"l_crop_irri":0.04,"l_urban":1.61,"p_population.y":13360,"area_km2.y":1001,"p_density_hkm2.y":13.35},{"county":"Alt Urgell","c_preci_mm":800.7,"c_wspeed_ms":71,"X7":"SW","year":2018,"c_temp_ave":11.7,"c_temp_avemax":19,"c_temp_avemin":5.9,"w_domestic_consump":45.6,"w_industry_consump":26.77,"w_total_network":72.37,"w_own_sources":41.92,"w_total":114.29,"p_population.x":20224,"area_km2.x":1447,"p_density_hkm2.x":13.98,"f_cleared_ha":0.01,"f_reforested_ha":0,"f_relative_reforested":4.94,"l_forests":56.13,"l_bushes":24.19,"l_others":12.08,"l_novege":2.02,"l_crop_dry":2.89,"l_crop_irri":1.25,"l_urban":1.47,"p_population.y":20224,"area_km2.y":1447,"p_density_hkm2.y":13.98},{"county":"Alta Ribagorça","c_preci_mm":1274.7,"c_wspeed_ms":79,"X7":"SE","year":2018,"c_temp_ave":10.1,"c_temp_avemax":18.9,"c_temp_avemin":3.6,"w_domestic_consump":130.74,"w_industry_consump":21.91,"w_total_network":152.65,"w_own_sources":18.92,"w_total":171.57,"p_population.x":3774,"area_km2.x":427,"p_density_hkm2.x":8.84,"f_cleared_ha":0,"f_reforested_ha":0,"l_forests":36.48,"l_bushes":17.93,"l_others":40.11,"l_novege":2.7,"l_crop_dry":1.37,"l_crop_irri":0.48,"l_urban":0.9,"p_population.y":3774,"area_km2.y":427,"p_density_hkm2.y":8.84},{"county":"Aran","c_preci_mm":1247.1,"c_wspeed_ms":78,"X7":"S","year":2018,"c_temp_ave":9.6,"c_temp_avemax":16.1,"c_temp_avemin":4.9,"w_domestic_consump":123.93,"w_industry_consump":29.39,"w_total_network":153.31,"w_own_sources":70.46,"w_total":223.77,"p_population.x":9983,"area_km2.x":634,"p_density_hkm2.x":15.75,"f_cleared_ha":0,"f_reforested_ha":0,"l_forests":37.4,"l_bushes":28.13,"l_others":31.78,"l_novege":1.47,"l_crop_dry":0.08,"l_crop_irri":0,"l_urban":1.09,"p_population.y":9983,"area_km2.y":634,"p_density_hkm2.y":15.75},{"county":"Berguedà","c_preci_mm":1303.4,"c_wspeed_ms":79,"X7":"SW","year":2018,"c_temp_ave":11.7,"c_temp_avemax":18.4,"c_temp_avemin":7.2,"w_domestic_consump":34.41,"w_industry_consump":17.95,"w_total_network":52.36,"w_own_sources":1.44,"w_total":53.8,"p_population.x":39104,"area_km2.x":1185,"p_density_hkm2.x":33,"f_cleared_ha":0.09,"f_reforested_ha":0,"f_relative_reforested":4.64,"l_forests":60.31,"l_bushes":15.35,"l_others":10.96,"l_novege":1.69,"l_crop_dry":9.57,"l_crop_irri":0.05,"l_urban":2.09,"p_population.y":39104,"area_km2.y":1185,"p_density_hkm2.y":33},{"county":"Cerdanya","c_preci_mm":828.2,"c_wspeed_ms":69,"X7":"NE","year":2018,"c_temp_ave":9.3,"c_temp_avemax":16.3,"c_temp_avemin":3.7,"w_domestic_consump":77.07,"w_industry_consump":27,"w_total_network":104.07,"w_own_sources":67.96,"w_total":172.03,"p_population.x":17882,"area_km2.x":547,"p_density_hkm2.x":32.69,"f_cleared_ha":0,"f_reforested_ha":0,"l_forests":45.78,"l_bushes":14.71,"l_others":27.51,"l_novege":1.95,"l_crop_dry":4.39,"l_crop_irri":1.76,"l_urban":3.83,"p_population.y":17882,"area_km2.y":547,"p_density_hkm2.y":32.69},{"county":"Pallars Jussà","c_preci_mm":954.7,"c_wspeed_ms":73,"X7":"N","year":2018,"c_temp_ave":12.8,"c_temp_avemax":19.9,"c_temp_avemin":7.2,"w_domestic_consump":60.24,"w_industry_consump":17.09,"w_total_network":77.33,"w_own_sources":6.74,"w_total":84.07,"p_population.x":13091,"area_km2.x":1343,"p_density_hkm2.x":9.75,"f_cleared_ha":0.04,"f_reforested_ha":0,"f_relative_reforested":2.14,"l_forests":33.58,"l_bushes":36.13,"l_others":12.25,"l_novege":3.02,"l_crop_dry":11.39,"l_crop_irri":1.97,"l_urban":1.66,"p_population.y":13091,"area_km2.y":1343,"p_density_hkm2.y":9.75},{"county":"Pallars Sobirà","c_preci_mm":961.1,"c_wspeed_ms":72,"X7":"..","year":2018,"c_temp_ave":11.7,"c_temp_avemax":19.1,"c_temp_avemin":5.7,"w_domestic_consump":78.76,"w_industry_consump":19.27,"w_total_network":98.02,"w_own_sources":71.36,"w_total":169.38,"p_population.x":6934,"area_km2.x":1378,"p_density_hkm2.x":5.03,"f_cleared_ha":0,"f_reforested_ha":0,"f_relative_reforested":0,"l_forests":44.72,"l_bushes":31.81,"l_others":20.34,"l_novege":1.3,"l_crop_dry":0.71,"l_crop_irri":0.1,"l_urban":1.01,"p_population.y":6934,"area_km2.y":1378,"p_density_hkm2.y":5.03},{"county":"Ripollès","c_preci_mm":1589.2,"c_wspeed_ms":82,"X7":"SW","year":2018,"c_temp_ave":10.4,"c_temp_avemax":17.2,"c_temp_avemin":4.8,"w_domestic_consump":41.76,"w_industry_consump":17.18,"w_total_network":58.94,"w_own_sources":30.43,"w_total":89.36,"p_population.x":25000,"area_km2.x":957,"p_density_hkm2.x":26.12,"f_cleared_ha":0,"f_reforested_ha":0,"l_forests":62.01,"l_bushes":11.98,"l_others":22.02,"l_novege":0.89,"l_crop_dry":1.39,"l_crop_irri":0,"l_urban":1.68,"p_population.y":25000,"area_km2.y":957,"p_density_hkm2.y":26.12},{"county":"Solsonès","c_preci_mm":898.6,"c_wspeed_ms":80,"X7":"W","year":2018,"c_temp_ave":12.3,"c_temp_avemax":18.1,"c_temp_avemin":7.4,"w_domestic_consump":42.14,"w_industry_consump":18.67,"w_total_network":60.81,"w_own_sources":26.87,"w_total":87.68,"p_population.x":13392,"area_km2.x":1001,"p_density_hkm2.x":13.38,"f_cleared_ha":0.12,"f_reforested_ha":0,"f_relative_reforested":0,"l_forests":58.44,"l_bushes":14.12,"l_others":4.8,"l_novege":1.7,"l_crop_dry":19.29,"l_crop_irri":0.06,"l_urban":1.61,"p_population.y":13392,"area_km2.y":1001,"p_density_hkm2.y":13.38},{"county":"Alt Urgell","c_preci_mm":592.2,"c_wspeed_ms":62,"X7":"SW","year":2019,"c_temp_ave":12.1,"c_temp_avemax":20.2,"c_temp_avemin":5.3,"w_domestic_consump":48.19,"w_industry_consump":28.89,"w_total_network":77.08,"w_own_sources":43.08,"w_total":120.16,"p_population.x":20177,"area_km2.x":1447,"p_density_hkm2.x":13.94,"f_cleared_ha":0.02,"f_reforested_ha":0.03,"f_relative_reforested":166.67,"l_forests":56.13,"l_bushes":24.19,"l_others":12.06,"l_novege":2.01,"l_crop_dry":2.91,"l_crop_irri":1.26,"l_urban":1.46,"p_population.y":20177,"area_km2.y":1447,"p_density_hkm2.y":13.94},{"county":"Alta Ribagorça","c_preci_mm":842.9,"c_wspeed_ms":71,"X7":"SE","year":2019,"c_temp_ave":10.4,"c_temp_avemax":20,"c_temp_avemin":2.8,"w_domestic_consump":128.62,"w_industry_consump":6.89,"w_total_network":135.51,"w_own_sources":46.5,"w_total":182.01,"p_population.x":3802,"area_km2.x":427,"p_density_hkm2.x":8.9,"f_cleared_ha":0.01,"f_reforested_ha":0,"f_relative_reforested":0,"l_forests":38.2,"l_bushes":17.96,"l_others":38.33,"l_novege":2.73,"l_crop_dry":1.36,"l_crop_irri":0.48,"l_urban":0.9,"p_population.y":3802,"area_km2.y":427,"p_density_hkm2.y":8.9},{"county":"Aran","c_preci_mm":1062.9,"c_wspeed_ms":73,"X7":"S","year":2019,"c_temp_ave":9.7,"c_temp_avemax":16.5,"c_temp_avemin":4.7,"w_domestic_consump":138,"w_industry_consump":27.37,"w_total_network":165.35,"w_own_sources":89.28,"w_total":254.64,"p_population.x":10093,"area_km2.x":634,"p_density_hkm2.x":15.92,"f_cleared_ha":0,"f_reforested_ha":0,"l_forests":37.4,"l_bushes":28.13,"l_others":31.78,"l_novege":1.47,"l_crop_dry":0.08,"l_crop_irri":0,"l_urban":1.08,"p_population.y":10093,"area_km2.y":634,"p_density_hkm2.y":15.92},{"county":"Berguedà","c_preci_mm":597,"c_wspeed_ms":71,"X7":"SW","year":2019,"c_temp_ave":12.3,"c_temp_avemax":19.8,"c_temp_avemin":7,"w_domestic_consump":35.22,"w_industry_consump":20.28,"w_total_network":55.5,"w_own_sources":1.44,"w_total":56.94,"p_population.x":39446,"area_km2.x":1185,"p_density_hkm2.x":33.29,"f_cleared_ha":0.14,"f_reforested_ha":0,"f_relative_reforested":0.2,"l_forests":60.31,"l_bushes":15.28,"l_others":10.89,"l_novege":1.69,"l_crop_dry":9.72,"l_crop_irri":0.05,"l_urban":2.08,"p_population.y":39446,"area_km2.y":1185,"p_density_hkm2.y":33.29},{"county":"Cerdanya","c_preci_mm":677.9,"c_wspeed_ms":60,"X7":"NE","year":2019,"c_temp_ave":9.9,"c_temp_avemax":17.3,"c_temp_avemin":3.6,"w_domestic_consump":78.74,"w_industry_consump":28.12,"w_total_network":106.85,"w_own_sources":87.35,"w_total":194.2,"p_population.x":18192,"area_km2.x":547,"p_density_hkm2.x":33.26,"f_cleared_ha":0,"f_reforested_ha":0,"l_forests":45.78,"l_bushes":14.71,"l_others":27.45,"l_novege":1.95,"l_crop_dry":4.39,"l_crop_irri":1.81,"l_urban":3.85,"p_population.y":18192,"area_km2.y":547,"p_density_hkm2.y":33.26},{"county":"Pallars Jussà","c_preci_mm":699.4,"c_wspeed_ms":65,"X7":"N","year":2019,"c_temp_ave":13.3,"c_temp_avemax":21.3,"c_temp_avemin":6.5,"w_domestic_consump":61.12,"w_industry_consump":17.84,"w_total_network":78.96,"w_own_sources":5.94,"w_total":84.9,"p_population.x":13080,"area_km2.x":1343,"p_density_hkm2.x":9.74,"f_cleared_ha":0.04,"f_reforested_ha":0,"f_relative_reforested":1.05,"l_forests":33.58,"l_bushes":36.13,"l_others":12.21,"l_novege":3.09,"l_crop_dry":11.36,"l_crop_irri":1.97,"l_urban":1.66,"p_population.y":13080,"area_km2.y":1343,"p_density_hkm2.y":9.74},{"county":"Pallars Sobirà","c_preci_mm":775.7,"c_wspeed_ms":64,"X7":"..","year":2019,"c_temp_ave":12.2,"c_temp_avemax":20.3,"c_temp_avemin":5.2,"w_domestic_consump":79.18,"w_industry_consump":20.35,"w_total_network":99.54,"w_own_sources":63.92,"w_total":163.46,"p_population.x":6932,"area_km2.x":1378,"p_density_hkm2.x":5.03,"f_cleared_ha":0,"f_reforested_ha":0,"f_relative_reforested":0,"l_forests":44.72,"l_bushes":31.81,"l_others":20.4,"l_novege":1.31,"l_crop_dry":0.64,"l_crop_irri":0.1,"l_urban":1.01,"p_population.y":6932,"area_km2.y":1378,"p_density_hkm2.y":5.03},{"county":"Ripollès","c_preci_mm":756.9,"c_wspeed_ms":76,"X7":"SW","year":2019,"c_temp_ave":10.6,"c_temp_avemax":18.1,"c_temp_avemin":4.1,"w_domestic_consump":42.95,"w_industry_consump":19.91,"w_total_network":62.87,"w_own_sources":38.22,"w_total":101.08,"p_population.x":25087,"area_km2.x":957,"p_density_hkm2.x":26.21,"f_cleared_ha":0,"f_reforested_ha":0,"l_forests":62.01,"l_bushes":11.98,"l_others":21.91,"l_novege":0.96,"l_crop_dry":1.39,"l_crop_irri":0,"l_urban":1.72,"p_population.y":25087,"area_km2.y":957,"p_density_hkm2.y":26.21},{"county":"Solsonès","c_preci_mm":522.1,"c_wspeed_ms":68,"X7":"W","year":2019,"c_temp_ave":13,"c_temp_avemax":21,"c_temp_avemin":6.4,"w_domestic_consump":42.34,"w_industry_consump":18.92,"w_total_network":61.25,"w_own_sources":23.49,"w_total":84.75,"p_population.x":13469,"area_km2.x":1001,"p_density_hkm2.x":13.46,"f_cleared_ha":0.21,"f_reforested_ha":0,"f_relative_reforested":0,"l_forests":58.44,"l_bushes":13.99,"l_others":4.68,"l_novege":1.71,"l_crop_dry":19.53,"l_crop_irri":0.06,"l_urban":1.61,"p_population.y":13469,"area_km2.y":1001,"p_density_hkm2.y":13.46},{"county":"Alt Urgell","c_preci_mm":632.5,"c_wspeed_ms":71,"X7":"SW","year":2020,"c_temp_ave":12,"c_temp_avemax":19.5,"c_temp_avemin":5.9,"w_domestic_consump":49.37,"w_industry_consump":18.65,"w_total_network":68.02,"w_own_sources":42.94,"w_total":110.97,"p_population.x":20231,"area_km2.x":1447,"p_density_hkm2.x":13.98,"f_cleared_ha":0.02,"f_reforested_ha":0,"f_relative_reforested":0,"l_forests":56.13,"l_bushes":24.19,"l_others":12.06,"l_novege":2.03,"l_crop_dry":2.89,"l_crop_irri":1.25,"l_urban":1.47,"p_population.y":20231,"area_km2.y":1447,"p_density_hkm2.y":13.98},{"county":"Alta Ribagorça","c_preci_mm":923.1,"c_wspeed_ms":79,"X7":"SE","year":2020,"c_temp_ave":10.5,"c_temp_avemax":19.6,"c_temp_avemin":3.7,"w_domestic_consump":120.84,"w_industry_consump":27.74,"w_total_network":148.58,"w_own_sources":58.2,"w_total":206.77,"p_population.x":3825,"area_km2.x":427,"p_density_hkm2.x":8.96,"f_cleared_ha":0.01,"f_reforested_ha":0,"f_relative_reforested":0,"l_forests":38.2,"l_bushes":17.82,"l_others":37.99,"l_novege":3.11,"l_crop_dry":1.47,"l_crop_irri":0.48,"l_urban":0.9,"p_population.y":3825,"area_km2.y":427,"p_density_hkm2.y":8.96},{"county":"Aran","c_preci_mm":1056.8,"X7":"S","year":2020,"c_temp_ave":10.2,"c_temp_avemax":17.2,"c_temp_avemin":5.5,"w_domestic_consump":138.02,"w_industry_consump":28.34,"w_total_network":166.37,"w_own_sources":74.62,"w_total":240.99,"p_population.x":10175,"area_km2.x":634,"p_density_hkm2.x":16.05,"f_cleared_ha":0,"f_reforested_ha":0,"l_forests":37.35,"l_bushes":28.17,"l_others":31.78,"l_novege":1.47,"l_crop_dry":0.07,"l_crop_irri":0,"l_urban":1.08,"p_population.y":10175,"area_km2.y":634,"p_density_hkm2.y":16.05},{"county":"Berguedà","c_preci_mm":1139.3,"c_wspeed_ms":78,"X7":"SW","year":2020,"c_temp_ave":12.1,"c_temp_avemax":18.8,"c_temp_avemin":7.6,"w_domestic_consump":37.24,"w_industry_consump":24.6,"w_total_network":61.84,"w_own_sources":1.64,"w_total":63.47,"p_population.x":39980,"area_km2.x":1185,"p_density_hkm2.x":33.74,"f_cleared_ha":0.11,"f_reforested_ha":0,"f_relative_reforested":0,"l_forests":60.28,"l_bushes":15.17,"l_others":10.84,"l_novege":1.72,"l_crop_dry":9.89,"l_crop_irri":0.05,"l_urban":2.07,"p_population.y":39980,"area_km2.y":1185,"p_density_hkm2.y":33.74},{"county":"Cerdanya","c_preci_mm":664.7,"c_wspeed_ms":66,"X7":"NE","year":2020,"c_temp_ave":10,"c_temp_avemax":17.2,"c_temp_avemin":4.1,"w_domestic_consump":78.82,"w_industry_consump":25.39,"w_total_network":104.21,"w_own_sources":67.22,"w_total":171.42,"p_population.x":18525,"area_km2.x":547,"p_density_hkm2.x":33.87,"f_cleared_ha":0,"f_reforested_ha":0,"l_forests":45.78,"l_bushes":14.71,"l_others":27.29,"l_novege":1.99,"l_crop_dry":4.44,"l_crop_irri":1.84,"l_urban":3.88,"p_population.y":18525,"area_km2.y":547,"p_density_hkm2.y":33.87},{"county":"Pallars Jussà","c_preci_mm":705.7,"c_wspeed_ms":72,"X7":"N","year":2020,"c_temp_ave":13.2,"c_temp_avemax":20.7,"c_temp_avemin":7.1,"w_domestic_consump":60.55,"w_industry_consump":11.5,"w_total_network":72.05,"w_own_sources":7.67,"w_total":79.72,"p_population.x":13227,"area_km2.x":1343,"p_density_hkm2.x":9.85,"f_cleared_ha":0.03,"f_reforested_ha":0,"f_relative_reforested":0,"l_forests":33.58,"l_bushes":36.13,"l_others":12.23,"l_novege":3.13,"l_crop_dry":11.31,"l_crop_irri":1.98,"l_urban":1.65,"p_population.y":13227,"area_km2.y":1343,"p_density_hkm2.y":9.85},{"county":"Pallars Sobirà","c_preci_mm":798,"c_wspeed_ms":72,"X7":"..","year":2020,"c_temp_ave":12,"c_temp_avemax":19.7,"c_temp_avemin":5.7,"w_domestic_consump":79.73,"w_industry_consump":21.36,"w_total_network":101.08,"w_own_sources":58.92,"w_total":160,"p_population.x":6930,"area_km2.x":1378,"p_density_hkm2.x":5.03,"f_cleared_ha":0,"f_reforested_ha":0,"f_relative_reforested":0,"l_forests":44.72,"l_bushes":31.71,"l_others":20.4,"l_novege":1.41,"l_crop_dry":0.64,"l_crop_irri":0.1,"l_urban":1.01,"p_population.y":6930,"area_km2.y":1378,"p_density_hkm2.y":5.03},{"county":"Ripollès","c_preci_mm":1551.8,"c_wspeed_ms":83,"X7":"SW","year":2020,"c_temp_ave":10.6,"c_temp_avemax":17.3,"c_temp_avemin":5,"w_domestic_consump":44.93,"w_industry_consump":16.65,"w_total_network":61.58,"w_own_sources":33.01,"w_total":94.59,"p_population.x":25253,"area_km2.x":957,"p_density_hkm2.x":26.39,"f_cleared_ha":0,"f_reforested_ha":0,"l_forests":62.01,"l_bushes":11.97,"l_others":21.89,"l_novege":0.98,"l_crop_dry":1.39,"l_crop_irri":0,"l_urban":1.72,"p_population.y":25253,"area_km2.y":957,"p_density_hkm2.y":26.39},{"county":"Solsonès","c_preci_mm":601.9,"c_wspeed_ms":75,"X7":"W","year":2020,"c_temp_ave":13,"c_temp_avemax":20.5,"c_temp_avemin":7,"w_domestic_consump":42.15,"w_industry_consump":21.79,"w_total_network":63.94,"w_own_sources":26.46,"w_total":90.41,"p_population.x":13513,"area_km2.x":1001,"p_density_hkm2.x":13.5,"f_cleared_ha":0.17,"f_reforested_ha":0,"f_relative_reforested":0,"l_forests":58.44,"l_bushes":13.99,"l_others":4.88,"l_novege":1.74,"l_crop_dry":19.29,"l_crop_irri":0.06,"l_urban":1.62,"p_population.y":13513,"area_km2.y":1001,"p_density_hkm2.y":13.5},{"county":"Alt Urgell","c_preci_mm":498.2,"c_wspeed_ms":68,"X7":"SW","year":2021,"c_temp_ave":11.8,"c_temp_avemax":19.5,"c_temp_avemin":5.4,"w_domestic_consump":51.49,"w_industry_consump":25.18,"w_total_network":76.68,"w_own_sources":44.08,"w_total":120.76,"p_population.x":20453,"area_km2.x":1447,"p_density_hkm2.x":14.13,"f_cleared_ha":0,"f_reforested_ha":0,"f_relative_reforested":0,"l_forests":56.13,"l_bushes":24.19,"l_others":11.83,"l_novege":2.34,"l_crop_dry":2.81,"l_crop_irri":1.25,"l_urban":1.47,"p_population.y":20453,"area_km2.y":1447,"p_density_hkm2.y":14.13},{"county":"Alta Ribagorça","c_preci_mm":756.9,"c_wspeed_ms":77,"X7":"SE","year":2021,"c_temp_ave":9.8,"c_temp_avemax":19.1,"c_temp_avemin":2.9,"w_domestic_consump":116.86,"w_industry_consump":12.95,"w_total_network":129.84,"w_own_sources":38.15,"w_total":167.98,"p_population.x":3945,"area_km2.x":427,"p_density_hkm2.x":9.24,"f_cleared_ha":0,"f_reforested_ha":0,"f_relative_reforested":0,"l_forests":36.9,"l_bushes":7.18,"l_others":49.83,"l_novege":3.16,"l_crop_dry":1.5,"l_crop_irri":0.48,"l_urban":0.91,"p_population.y":3945,"area_km2.y":427,"p_density_hkm2.y":9.24},{"county":"Aran","c_preci_mm":889.7,"c_wspeed_ms":76,"X7":"S","year":2021,"c_temp_ave":9.5,"c_temp_avemax":16.4,"c_temp_avemin":4.7,"w_domestic_consump":134.19,"w_industry_consump":26.74,"w_total_network":160.92,"w_own_sources":62.78,"w_total":223.71,"p_population.x":10372,"area_km2.x":634,"p_density_hkm2.x":16.36,"f_cleared_ha":0,"f_reforested_ha":0,"l_forests":37.35,"l_bushes":28.17,"l_others":31.78,"l_novege":1.47,"l_crop_dry":0.07,"l_crop_irri":0,"l_urban":1.08,"p_population.y":10372,"area_km2.y":634,"p_density_hkm2.y":16.36},{"county":"Berguedà","c_preci_mm":612,"c_wspeed_ms":77,"X7":"SW","year":2021,"c_temp_ave":11.8,"c_temp_avemax":18.8,"c_temp_avemin":7.1,"w_domestic_consump":37.23,"w_industry_consump":25.19,"w_total_network":62.42,"w_own_sources":1.25,"w_total":63.68,"p_population.x":40004,"area_km2.x":1185,"p_density_hkm2.x":33.76,"f_cleared_ha":0.12,"f_reforested_ha":0,"f_relative_reforested":0,"l_forests":60.28,"l_bushes":15.08,"l_others":10.82,"l_novege":1.72,"l_crop_dry":10.02,"l_crop_irri":0.05,"l_urban":2.06,"p_population.y":40004,"area_km2.y":1185,"p_density_hkm2.y":33.76},{"county":"Cerdanya","c_preci_mm":656.7,"c_wspeed_ms":66,"X7":"NE","year":2021,"c_temp_ave":9.5,"c_temp_avemax":16.8,"c_temp_avemin":3.5,"w_domestic_consump":73.47,"w_industry_consump":26.01,"w_total_network":99.49,"w_own_sources":80.79,"w_total":180.27,"p_population.x":19230,"area_km2.x":547,"p_density_hkm2.x":35.16,"f_cleared_ha":0,"f_reforested_ha":0,"l_forests":45.79,"l_bushes":14.71,"l_others":27.33,"l_novege":2,"l_crop_dry":4.39,"l_crop_irri":1.86,"l_urban":3.87,"p_population.y":19230,"area_km2.y":547,"p_density_hkm2.y":35.16},{"county":"Pallars Jussà","c_preci_mm":603.6,"c_wspeed_ms":69,"X7":"N","year":2021,"c_temp_ave":12.8,"c_temp_avemax":20.6,"c_temp_avemin":6.5,"w_domestic_consump":61.34,"w_industry_consump":12.55,"w_total_network":73.9,"w_own_sources":7.01,"w_total":80.9,"p_population.x":13170,"area_km2.x":1343,"p_density_hkm2.x":9.81,"f_cleared_ha":0.03,"f_reforested_ha":0,"f_relative_reforested":0,"l_forests":33.58,"l_bushes":36.13,"l_others":12.13,"l_novege":3.24,"l_crop_dry":11.27,"l_crop_irri":1.99,"l_urban":1.67,"p_population.y":13170,"area_km2.y":1343,"p_density_hkm2.y":9.81},{"county":"Pallars Sobirà","c_preci_mm":749.7,"c_wspeed_ms":70,"X7":"..","year":2021,"c_temp_ave":11.7,"c_temp_avemax":19.6,"c_temp_avemin":5.1,"w_domestic_consump":78.47,"w_industry_consump":17.1,"w_total_network":95.55,"w_own_sources":62.55,"w_total":158.1,"p_population.x":7101,"area_km2.x":1378,"p_density_hkm2.x":5.15,"f_cleared_ha":0,"f_reforested_ha":0,"l_forests":44.72,"l_bushes":31.71,"l_others":20.4,"l_novege":1.41,"l_crop_dry":0.64,"l_crop_irri":0.1,"l_urban":1.01,"p_population.y":7101,"area_km2.y":1378,"p_density_hkm2.y":5.15},{"county":"Ripollès","c_preci_mm":1008.9,"c_wspeed_ms":84,"X7":"SW","year":2021,"c_temp_ave":10.3,"c_temp_avemax":16.8,"c_temp_avemin":4.9,"w_domestic_consump":44.45,"w_industry_consump":17.71,"w_total_network":62.16,"w_own_sources":25.91,"w_total":88.07,"p_population.x":25449,"area_km2.x":957,"p_density_hkm2.x":26.59,"f_cleared_ha":0,"f_reforested_ha":0,"l_forests":62.01,"l_bushes":11.97,"l_others":21.88,"l_novege":0.99,"l_crop_dry":1.37,"l_crop_irri":0,"l_urban":1.74,"p_population.y":25449,"area_km2.y":957,"p_density_hkm2.y":26.59},{"county":"Solsonès","c_preci_mm":486.1,"c_wspeed_ms":73,"X7":"W","year":2021,"c_temp_ave":12.7,"c_temp_avemax":20.6,"c_temp_avemin":6.6,"w_domestic_consump":41.79,"w_industry_consump":24.32,"w_total_network":66.1,"w_own_sources":27.46,"w_total":93.55,"p_population.x":13600,"area_km2.x":1001,"p_density_hkm2.x":13.59,"f_cleared_ha":0.24,"f_reforested_ha":0,"f_relative_reforested":0,"l_forests":58.44,"l_bushes":13.98,"l_others":4.86,"l_novege":1.74,"l_crop_dry":19.3,"l_crop_irri":0.07,"l_urban":1.63,"p_population.y":13600,"area_km2.y":1001,"p_density_hkm2.y":13.59},{"county":"Alt Urgell","c_preci_mm":529.5,"c_wspeed_ms":64,"X7":"SW","year":2022,"c_temp_ave":13,"c_temp_avemax":21.2,"c_temp_avemin":6.4,"w_domestic_consump":49.63,"w_industry_consump":31.94,"w_total_network":81.56,"w_own_sources":39.69,"w_total":121.26,"p_population.x":20482,"area_km2.x":1447,"p_density_hkm2.x":14.15,"f_cleared_ha":0,"f_reforested_ha":0,"f_relative_reforested":64.1,"l_forests":56.12,"l_bushes":24.18,"l_others":11.86,"l_novege":2.37,"l_crop_dry":2.71,"l_crop_irri":1.22,"l_urban":1.47,"p_population.y":20482,"area_km2.y":1447,"p_density_hkm2.y":14.15},{"county":"Alta Ribagorça","c_preci_mm":686.8,"c_wspeed_ms":73,"X7":"SE","year":2022,"c_temp_ave":11.1,"c_temp_avemax":20.8,"c_temp_avemin":3.9,"w_domestic_consump":118.52,"w_industry_consump":9.27,"w_total_network":127.79,"w_own_sources":59.35,"w_total":187.14,"p_population.x":3958,"area_km2.x":427,"p_density_hkm2.x":9.27,"f_cleared_ha":0,"f_reforested_ha":0,"f_relative_reforested":0,"l_forests":36.9,"l_bushes":5.74,"l_others":51.46,"l_novege":3.18,"l_crop_dry":1.56,"l_crop_irri":0.46,"l_urban":0.91,"p_population.y":3958,"area_km2.y":427,"p_density_hkm2.y":9.27},{"county":"Aran","c_preci_mm":904.5,"c_wspeed_ms":69,"X7":"S","year":2022,"c_temp_ave":11.5,"c_temp_avemax":19,"c_temp_avemin":5.9,"w_domestic_consump":136.14,"w_industry_consump":27.06,"w_total_network":163.21,"w_own_sources":60.91,"w_total":224.11,"p_population.x":10268,"area_km2.x":634,"p_density_hkm2.x":16.2,"f_cleared_ha":0,"f_reforested_ha":0,"l_forests":37.36,"l_bushes":27.92,"l_others":31.79,"l_novege":1.49,"l_crop_dry":0.07,"l_crop_irri":0,"l_urban":1.08,"p_population.y":10268,"area_km2.y":634,"p_density_hkm2.y":16.2},{"county":"Berguedà","c_preci_mm":707.8,"c_wspeed_ms":70,"X7":"SW","year":2022,"c_temp_ave":13.4,"c_temp_avemax":20.5,"c_temp_avemin":8.6,"w_domestic_consump":35.6,"w_industry_consump":25.28,"w_total_network":60.88,"w_own_sources":1.27,"w_total":62.14,"p_population.x":40279,"area_km2.x":1185,"p_density_hkm2.x":33.99,"f_cleared_ha":0.08,"f_reforested_ha":0,"f_relative_reforested":0,"l_forests":60.29,"l_bushes":14.93,"l_others":10.81,"l_novege":1.85,"l_crop_dry":10.13,"l_crop_irri":0.05,"l_urban":2.05,"p_population.y":40279,"area_km2.y":1185,"p_density_hkm2.y":33.99},{"county":"Cerdanya","c_preci_mm":444.7,"c_wspeed_ms":64,"X7":"NE","year":2022,"c_temp_ave":10.8,"c_temp_avemax":18.5,"c_temp_avemin":4.6,"w_domestic_consump":74.67,"w_industry_consump":27.85,"w_total_network":102.52,"w_own_sources":80.68,"w_total":183.19,"p_population.x":19443,"area_km2.x":547,"p_density_hkm2.x":35.54,"f_cleared_ha":0,"f_reforested_ha":0,"l_forests":45.79,"l_bushes":14.71,"l_others":27,"l_novege":2.16,"l_crop_dry":4.47,"l_crop_irri":1.85,"l_urban":3.88,"p_population.y":19443,"area_km2.y":547,"p_density_hkm2.y":35.54},{"county":"Pallars Jussà","c_preci_mm":511,"c_wspeed_ms":68,"X7":"W","year":2022,"c_temp_ave":14.4,"c_temp_avemax":22.7,"c_temp_avemin":7.5,"w_domestic_consump":62.48,"w_industry_consump":12.9,"w_total_network":75.38,"w_own_sources":5.95,"w_total":81.34,"p_population.x":13199,"area_km2.x":1343,"p_density_hkm2.x":9.83,"f_cleared_ha":0.03,"f_reforested_ha":0,"f_relative_reforested":0,"l_forests":33.61,"l_bushes":36.03,"l_others":12.15,"l_novege":3.33,"l_crop_dry":11.25,"l_crop_irri":1.91,"l_urban":1.67,"p_population.y":13199,"area_km2.y":1343,"p_density_hkm2.y":9.83},{"county":"Pallars Sobirà","c_preci_mm":489.7,"c_wspeed_ms":67,"X7":"..","year":2022,"c_temp_ave":13,"c_temp_avemax":21.4,"c_temp_avemin":6.2,"w_domestic_consump":77.64,"w_industry_consump":19.89,"w_total_network":97.52,"w_own_sources":58.26,"w_total":155.79,"p_population.x":7181,"area_km2.x":1378,"p_density_hkm2.x":5.21,"f_cleared_ha":0,"f_reforested_ha":0,"f_relative_reforested":0,"l_forests":44.72,"l_bushes":31.71,"l_others":20.72,"l_novege":1.44,"l_crop_dry":0.67,"l_crop_irri":0.1,"l_urban":1,"p_population.y":7181,"area_km2.y":1378,"p_density_hkm2.y":5.21},{"county":"Ripollès","c_preci_mm":842.7,"c_wspeed_ms":79,"X7":"SW","year":2022,"c_temp_ave":11.4,"c_temp_avemax":18.9,"c_temp_avemin":5.2,"w_domestic_consump":42.87,"w_industry_consump":18.1,"w_total_network":60.97,"w_own_sources":33.33,"w_total":94.3,"p_population.x":25510,"area_km2.x":957,"p_density_hkm2.x":26.66,"f_cleared_ha":0,"f_reforested_ha":0,"l_forests":62.08,"l_bushes":12.02,"l_others":21.91,"l_novege":1.04,"l_crop_dry":1.28,"l_crop_irri":0.01,"l_urban":1.73,"p_population.y":25510,"area_km2.y":957,"p_density_hkm2.y":26.66},{"county":"Solsonès","c_preci_mm":576.6,"c_wspeed_ms":69,"X7":"W","year":2022,"c_temp_ave":14.1,"c_temp_avemax":22.1,"c_temp_avemin":7.7,"w_domestic_consump":41.78,"w_industry_consump":27.67,"w_total_network":69.45,"w_own_sources":26.51,"w_total":95.96,"p_population.x":13632,"area_km2.x":1001,"p_density_hkm2.x":13.62,"f_cleared_ha":0.18,"f_reforested_ha":0,"f_relative_reforested":0,"l_forests":58.42,"l_bushes":13.86,"l_others":4.87,"l_novege":1.78,"l_crop_dry":19.37,"l_crop_irri":0.06,"l_urban":1.63,"p_population.y":13632,"area_km2.y":1001,"p_density_hkm2.y":13.62},{"county":"Alt Urgell","c_preci_mm":425.5,"c_wspeed_ms":61,"X7":"SW","year":2023,"c_temp_ave":13,"c_temp_avemax":21.1,"c_temp_avemin":6.4,"w_domestic_consump":47.91,"w_industry_consump":29.63,"w_total_network":77.54,"w_own_sources":36.3,"w_total":113.84,"p_population.x":20762,"area_km2.x":1447,"p_density_hkm2.x":14.35,"f_reforested_ha":0,"l_forests":56.12,"l_bushes":24.18,"l_others":11.86,"l_novege":2.35,"l_crop_dry":2.67,"l_crop_irri":1.24,"l_urban":1.47,"p_population.y":20762,"area_km2.y":1447,"p_density_hkm2.y":14.35},{"county":"Alta Ribagorça","c_preci_mm":787.8,"c_wspeed_ms":72,"X7":"SE","year":2023,"c_temp_ave":10.8,"c_temp_avemax":20.6,"c_temp_avemin":3.5,"w_domestic_consump":116.07,"w_industry_consump":9.21,"w_total_network":125.28,"w_own_sources":52.77,"w_total":178.05,"p_population.x":4019,"area_km2.x":427,"p_density_hkm2.x":9.41,"f_reforested_ha":0,"l_forests":36.9,"l_bushes":5.74,"l_others":51.46,"l_novege":3.15,"l_crop_dry":1.56,"l_crop_irri":0.44,"l_urban":0.91,"p_population.y":4019,"area_km2.y":427,"p_density_hkm2.y":9.41},{"county":"Aran","c_preci_mm":851.6,"c_wspeed_ms":72,"X7":"S","year":2023,"c_temp_ave":10.8,"c_temp_avemax":18.2,"c_temp_avemin":5.2,"w_domestic_consump":133.84,"w_industry_consump":26.98,"w_total_network":160.82,"w_own_sources":76.05,"w_total":236.88,"p_population.x":10496,"area_km2.x":634,"p_density_hkm2.x":16.56,"f_reforested_ha":0,"l_forests":37.36,"l_bushes":27.92,"l_others":31.79,"l_novege":1.47,"l_crop_dry":0.08,"l_crop_irri":0,"l_urban":1.08,"p_population.y":10496,"area_km2.y":634,"p_density_hkm2.y":16.56},{"county":"Berguedà","c_preci_mm":566.1,"c_wspeed_ms":69,"X7":"SW","year":2023,"c_temp_ave":13,"c_temp_avemax":20.2,"c_temp_avemin":8,"w_domestic_consump":33.93,"w_industry_consump":28.84,"w_total_network":62.77,"w_own_sources":1.1,"w_total":63.87,"p_population.x":40618,"area_km2.x":1185,"p_density_hkm2.x":34.28,"f_reforested_ha":0,"l_forests":60.29,"l_bushes":14.93,"l_others":10.81,"l_novege":1.83,"l_crop_dry":10.19,"l_crop_irri":0.04,"l_urban":2.05,"p_population.y":40618,"area_km2.y":1185,"p_density_hkm2.y":34.28},{"county":"Cerdanya","c_preci_mm":317.2,"c_wspeed_ms":60,"X7":"NE","year":2023,"c_temp_ave":10.9,"c_temp_avemax":18.5,"c_temp_avemin":4.5,"w_domestic_consump":69.65,"w_industry_consump":26.52,"w_total_network":96.17,"w_own_sources":87.73,"w_total":183.9,"p_population.x":19885,"area_km2.x":547,"p_density_hkm2.x":36.35,"f_reforested_ha":0,"l_forests":45.79,"l_bushes":14.71,"l_others":27,"l_novege":2.14,"l_crop_dry":4.96,"l_crop_irri":1.39,"l_urban":3.88,"p_population.y":19885,"area_km2.y":547,"p_density_hkm2.y":36.35},{"county":"Pallars Jussà","c_preci_mm":429.3,"c_wspeed_ms":66,"X7":"W","year":2023,"c_temp_ave":14.2,"c_temp_avemax":22.8,"c_temp_avemin":7.1,"w_domestic_consump":60.88,"w_industry_consump":12.3,"w_total_network":73.17,"w_own_sources":6.44,"w_total":79.61,"p_population.x":13409,"area_km2.x":1343,"p_density_hkm2.x":9.98,"f_reforested_ha":0,"l_forests":33.61,"l_bushes":36.03,"l_others":12.15,"l_novege":3.3,"l_crop_dry":11.27,"l_crop_irri":1.9,"l_urban":1.64,"p_population.y":13409,"area_km2.y":1343,"p_density_hkm2.y":9.98},{"county":"Pallars Sobirà","c_preci_mm":598.4,"c_wspeed_ms":66,"X7":"..","year":2023,"c_temp_ave":12.7,"c_temp_avemax":21.1,"c_temp_avemin":5.8,"w_domestic_consump":79.49,"w_industry_consump":22.63,"w_total_network":102.11,"w_own_sources":59.4,"w_total":161.51,"p_population.x":7288,"area_km2.x":1378,"p_density_hkm2.x":5.29,"f_reforested_ha":0,"l_forests":44.72,"l_bushes":31.71,"l_others":20.72,"l_novege":1.43,"l_crop_dry":0.69,"l_crop_irri":0.1,"l_urban":1,"p_population.y":7288,"area_km2.y":1378,"p_density_hkm2.y":5.29},{"county":"Ripollès","c_preci_mm":706.1,"c_wspeed_ms":75,"X7":"SW","year":2023,"c_temp_ave":11.3,"c_temp_avemax":18.9,"c_temp_avemin":5,"w_domestic_consump":42.21,"w_industry_consump":18.2,"w_total_network":60.4,"w_own_sources":28.75,"w_total":89.15,"p_population.x":25780,"area_km2.x":957,"p_density_hkm2.x":26.94,"f_reforested_ha":0,"l_forests":62.08,"l_bushes":12.02,"l_others":21.91,"l_novege":1.03,"l_crop_dry":1.3,"l_crop_irri":0,"l_urban":1.73,"p_population.y":25780,"area_km2.y":957,"p_density_hkm2.y":26.94},{"county":"Solsonès","c_preci_mm":331.5,"c_wspeed_ms":67,"X7":"W","year":2023,"c_temp_ave":13.9,"c_temp_avemax":22.1,"c_temp_avemin":7.3,"w_domestic_consump":43.12,"w_industry_consump":27.71,"w_total_network":70.83,"w_own_sources":27.94,"w_total":98.78,"p_population.x":13725,"area_km2.x":1001,"p_density_hkm2.x":13.71,"f_reforested_ha":0,"l_forests":58.42,"l_bushes":13.86,"l_others":4.87,"l_novege":1.57,"l_crop_dry":25.32,"l_crop_irri":0.07,"l_urban":1.27,"p_population.y":13725,"area_km2.y":1001,"p_density_hkm2.y":13.71},{"county":"Alt Urgell","c_preci_mm":777.5,"c_wspeed_ms":66,"X7":"SW","year":2024,"c_temp_ave":12.7,"c_temp_avemax":20.1,"c_temp_avemin":6.6,"w_domestic_consump":47.67,"w_industry_consump":31.33,"w_total_network":78.99,"w_own_sources":30.18,"w_total":109.17,"p_population.x":21128,"area_km2.x":1447,"p_density_hkm2.x":14.6,"p_population.y":21128,"area_km2.y":1447,"p_density_hkm2.y":14.6},{"county":"Alta Ribagorça","c_preci_mm":1197.3,"c_wspeed_ms":76,"X7":"SE","year":2024,"c_temp_ave":10.9,"c_temp_avemax":20,"c_temp_avemin":4.1,"w_domestic_consump":115.54,"w_industry_consump":30.57,"w_total_network":146.11,"w_own_sources":75.77,"w_total":221.88,"p_population.x":4040,"area_km2.x":427,"p_density_hkm2.x":9.46,"p_population.y":4040,"area_km2.y":427,"p_density_hkm2.y":9.46},{"county":"Aran","c_preci_mm":945.7,"c_wspeed_ms":74,"X7":"S","year":2024,"c_temp_ave":10.8,"c_temp_avemax":17.5,"c_temp_avemin":5.5,"w_domestic_consump":133.13,"w_industry_consump":26.93,"w_total_network":160.08,"w_own_sources":68.5,"w_total":228.57,"p_population.x":10545,"area_km2.x":634,"p_density_hkm2.x":16.63,"p_population.y":10545,"area_km2.y":634,"p_density_hkm2.y":16.63},{"county":"Berguedà","c_preci_mm":948,"c_wspeed_ms":73,"X7":"SW","year":2024,"c_temp_ave":12.6,"c_temp_avemax":19.1,"c_temp_avemin":7.8,"w_domestic_consump":34.09,"w_industry_consump":27.03,"w_total_network":61.12,"w_own_sources":1.05,"w_total":62.17,"p_population.x":41058,"area_km2.x":1185,"p_density_hkm2.x":34.65,"p_population.y":41058,"area_km2.y":1185,"p_density_hkm2.y":34.65},{"county":"Cerdanya","c_preci_mm":631.7,"c_wspeed_ms":65,"X7":"SW","year":2024,"c_temp_ave":10.6,"c_temp_avemax":17.8,"c_temp_avemin":4.7,"w_domestic_consump":70.58,"w_industry_consump":26.53,"w_total_network":97.11,"w_own_sources":83.73,"w_total":180.84,"p_population.x":20115,"area_km2.x":547,"p_density_hkm2.x":36.77,"p_population.y":20115,"area_km2.y":547,"p_density_hkm2.y":36.77},{"county":"Pallars Jussà","c_preci_mm":645.5,"c_wspeed_ms":70,"X7":"W","year":2024,"c_temp_ave":14.2,"c_temp_avemax":21.9,"c_temp_avemin":7.5,"w_domestic_consump":59.63,"w_industry_consump":12.69,"w_total_network":72.32,"w_own_sources":8.48,"w_total":80.8,"p_population.x":13383,"area_km2.x":1343,"p_density_hkm2.x":9.97,"p_population.y":13383,"area_km2.y":1343,"p_density_hkm2.y":9.97},{"county":"Pallars Sobirà","c_preci_mm":800.5,"c_wspeed_ms":70,"X7":"..","year":2024,"c_temp_ave":12.8,"c_temp_avemax":20.8,"c_temp_avemin":6.4,"w_domestic_consump":77.82,"w_industry_consump":27.7,"w_total_network":105.52,"w_own_sources":68.4,"w_total":173.91,"p_population.x":7332,"area_km2.x":1378,"p_density_hkm2.x":5.32,"p_population.y":7332,"area_km2.y":1378,"p_density_hkm2.y":5.32},{"county":"Ripollès","c_preci_mm":1117.6,"c_wspeed_ms":79,"X7":"SW","year":2024,"c_temp_ave":11.3,"c_temp_avemax":18.5,"c_temp_avemin":5.5,"w_domestic_consump":40.89,"w_industry_consump":19.16,"w_total_network":60.05,"w_own_sources":23.98,"w_total":84.03,"p_population.x":25826,"area_km2.x":957,"p_density_hkm2.x":26.99,"p_population.y":25826,"area_km2.y":957,"p_density_hkm2.y":26.99},{"county":"Solsonès","c_preci_mm":584.9,"c_wspeed_ms":72,"X7":"W","year":2024,"c_temp_ave":13.6,"c_temp_avemax":21.2,"c_temp_avemin":7.5,"w_domestic_consump":36.94,"w_industry_consump":22.14,"w_total_network":59.08,"w_own_sources":21.18,"w_total":80.26,"p_population.x":15323,"area_km2.x":1161,"p_density_hkm2.x":13.2,"p_population.y":15323,"area_km2.y":1161,"p_density_hkm2.y":13.2},{"county":"Catalunya","c_preci_mm":455.41,"c_wspeed_ms":69.12,"year":2015,"c_temp_ave":14.48,"c_temp_avemax":21.13,"c_temp_avemin":8.88,"w_domestic_consump":41.82,"w_industry_consump":22.15,"w_total_network":63.97,"w_own_sources":12.66,"w_total":76.63,"p_population.x":7508106,"area_km2.x":32112,"p_density_hkm2.x":233.81,"f_cleared_ha":0.11,"f_reforested_ha":0.01,"f_relative_reforested":8.53,"l_forests":34.85,"l_bushes":22.31,"l_others":6.83,"l_novege":3.25,"l_crop_dry":17.72,"l_crop_irri":8.28,"l_urban":6.71,"p_population.y":7508106,"area_km2.y":32112,"p_density_hkm2.y":233.81},{"county":"Catalunya","c_preci_mm":513.22,"c_wspeed_ms":69.95,"year":2016,"c_temp_ave":14.37,"c_temp_avemax":20.77,"c_temp_avemin":8.89,"w_domestic_consump":42.33,"w_industry_consump":23.22,"w_total_network":65.55,"w_own_sources":12.59,"w_total":78.14,"p_population.x":7522596,"area_km2.x":32111,"p_density_hkm2.x":234.27,"f_cleared_ha":0.13,"f_reforested_ha":0.01,"f_relative_reforested":11.17,"l_forests":34.86,"l_bushes":22.29,"l_others":6.84,"l_novege":3.24,"l_crop_dry":17.56,"l_crop_irri":8.41,"l_urban":6.72,"p_population.y":7522596,"area_km2.y":32111,"p_density_hkm2.y":234.27},{"county":"Catalunya","c_preci_mm":436.48,"c_wspeed_ms":68.15,"year":2017,"c_temp_ave":14.43,"c_temp_avemax":21.19,"c_temp_avemin":8.62,"w_domestic_consump":42.56,"w_industry_consump":23.93,"w_total_network":66.49,"w_own_sources":12.75,"w_total":79.23,"p_population.x":7555830,"area_km2.x":32110,"p_density_hkm2.x":235.31,"f_cleared_ha":0.12,"f_reforested_ha":0.02,"f_relative_reforested":14.99,"l_forests":34.85,"l_bushes":22.28,"l_others":6.86,"l_novege":3.29,"l_crop_dry":17.51,"l_crop_irri":8.37,"l_urban":6.78,"p_population.y":7555830,"area_km2.y":32110,"p_density_hkm2.y":235.31},{"county":"Catalunya","c_preci_mm":868.89,"c_wspeed_ms":73.05,"year":2018,"c_temp_ave":14.41,"c_temp_avemax":20.63,"c_temp_avemin":9.17,"w_domestic_consump":42.21,"w_industry_consump":23.17,"w_total_network":65.38,"w_own_sources":12.31,"w_total":77.68,"p_population.x":7600065,"area_km2.x":32110,"p_density_hkm2.x":236.69,"f_cleared_ha":0.09,"f_reforested_ha":0.01,"f_relative_reforested":11.5,"l_forests":34.95,"l_bushes":22.19,"l_others":6.72,"l_novege":3.37,"l_crop_dry":17.53,"l_crop_irri":8.43,"l_urban":6.8,"p_population.y":7600065,"area_km2.y":32110,"p_density_hkm2.y":236.69},{"county":"Catalunya","c_preci_mm":514.17,"c_wspeed_ms":68.07,"year":2019,"c_temp_ave":14.51,"c_temp_avemax":21.25,"c_temp_avemin":8.63,"w_domestic_consump":42.55,"w_industry_consump":23.51,"w_total_network":66.06,"w_own_sources":12.07,"w_total":78.13,"p_population.x":7675217,"area_km2.x":32110,"p_density_hkm2.x":239.03,"f_cleared_ha":0.1,"f_reforested_ha":0.02,"f_relative_reforested":17.86,"l_forests":35.05,"l_bushes":22.12,"l_others":6.61,"l_novege":3.51,"l_crop_dry":17.41,"l_crop_irri":8.46,"l_urban":6.83,"p_population.y":7675217,"area_km2.y":32110,"p_density_hkm2.y":239.03},{"county":"Catalunya","c_preci_mm":771.99,"c_wspeed_ms":73.95,"year":2020,"c_temp_ave":14.59,"c_temp_avemax":20.96,"c_temp_avemin":9.18,"w_domestic_consump":44.36,"w_industry_consump":18.87,"w_total_network":63.23,"w_own_sources":11.21,"w_total":74.44,"p_population.x":7780479,"area_km2.x":32110,"p_density_hkm2.x":242.31,"f_cleared_ha":0.09,"f_reforested_ha":0,"f_relative_reforested":5.05,"l_forests":35.01,"l_bushes":22.15,"l_others":6.59,"l_novege":3.6,"l_crop_dry":17.29,"l_crop_irri":8.52,"l_urban":6.83,"p_population.y":7780479,"area_km2.y":32110,"p_density_hkm2.y":242.31},{"county":"Catalunya","c_preci_mm":487.37,"c_wspeed_ms":73.02,"year":2021,"c_temp_ave":14.23,"c_temp_avemax":20.6,"c_temp_avemin":8.82,"w_domestic_consump":43.57,"w_industry_consump":20.61,"w_total_network":64.17,"w_own_sources":11.3,"w_total":75.47,"p_population.x":7763362,"area_km2.x":32110,"p_density_hkm2.x":241.77,"f_cleared_ha":0.1,"f_reforested_ha":0.01,"f_relative_reforested":13.73,"l_forests":35.02,"l_bushes":22.01,"l_others":6.74,"l_novege":3.6,"l_crop_dry":17.22,"l_crop_irri":8.6,"l_urban":6.82,"p_population.y":7763362,"area_km2.y":32110,"p_density_hkm2.y":241.77},{"county":"Catalunya","c_preci_mm":445.79,"c_wspeed_ms":69.73,"year":2022,"c_temp_ave":15.63,"c_temp_avemax":22.41,"c_temp_avemin":9.91,"w_domestic_consump":42.48,"w_industry_consump":22.88,"w_total_network":65.36,"w_own_sources":11.15,"w_total":76.51,"p_population.x":7792611,"area_km2.x":32110,"p_density_hkm2.x":242.68,"f_cleared_ha":0.08,"f_reforested_ha":0.01,"f_relative_reforested":6.94,"l_forests":35,"l_bushes":21.87,"l_others":6.73,"l_novege":3.99,"l_crop_dry":17.07,"l_crop_irri":8.53,"l_urban":6.82,"p_population.y":7792611,"area_km2.y":32110,"p_density_hkm2.y":242.68},{"county":"Catalunya","c_preci_mm":382.39,"c_wspeed_ms":67.85,"year":2023,"c_temp_ave":15.39,"c_temp_avemax":22.32,"c_temp_avemin":9.53,"w_domestic_consump":40.78,"w_industry_consump":21.73,"w_total_network":62.51,"w_own_sources":10.18,"w_total":72.69,"p_population.x":7901963,"area_km2.x":32110,"p_density_hkm2.x":246.09,"f_reforested_ha":0,"l_forests":34.51,"l_bushes":21.56,"l_others":6.68,"l_novege":3.82,"l_crop_dry":16.94,"l_crop_irri":8.14,"l_urban":6.69,"p_population.y":7901963,"area_km2.y":32110,"p_density_hkm2.y":246.09},{"county":"Catalunya","c_preci_mm":683.93,"c_wspeed_ms":71.66,"year":2024,"c_temp_ave":15.22,"c_temp_avemax":21.58,"c_temp_avemin":9.75,"w_domestic_consump":39.18,"w_industry_consump":20.09,"w_total_network":59.27,"w_own_sources":9.06,"w_total":68.34,"p_population.x":8012231,"area_km2.x":32111,"p_density_hkm2.x":249.52,"p_population.y":8012231,"area_km2.y":32111,"p_density_hkm2.y":249.52}]
